libcdb/__init__.py
libcdb/libcdb.py
libcdb-0.1.dist-info/METADATA
libcdb-0.1.dist-info/RECORD
libcdb-0.1.dist-info/WHEEL
libcdb-0.1.dist-info/top_level.txt
