Metadata-Version: 2.1
Name: libcdb
Version: 0.1
Summary: A libc search utility based on https://libc.ml/
Home-page: https://github.com/unamer/libcdb
Author: nonick
Author-email: n0nick@protonmail.com
License: GNU LGPLv3
Platform: UNKNOWN
Classifier: Development Status :: 4 - Beta
Classifier: Intended Audience :: Developers
Classifier: License :: OSI Approved :: GNU Lesser General Public License v3 (LGPLv3)
Classifier: Programming Language :: Python :: 2
Classifier: Programming Language :: Python :: 3
Requires-Dist: requests
